{
  "owner": "andresilvagomez",
  "name": "Localize",
  "description": "Localize is a framework writed in swift to localize your projects easier improves i18n, including storyboards and strings.",
  "url": "https://github.com/andresilvagomez/Localize",
  "homepage_url": "",
  "language": "Swift",
  "license": "MIT",
  "topics": [
    "swift",
    "localization",
    "localized",
    "xcode",
    "cocoapods",
    "json",
    "carthage",
    "storyboards",
    "language",
    "storyboard",
    "apple-strings",
    "swift4"
  ],
  "fork_count": 49,
  "star_count": 293,
  "is_archived": false,
  "star_history": [
    {
      "date": "2026-04-14",
      "stars": 293
    }
  ]
}