{
  "repo_id": "MDEwOlJlcG9zaXRvcnk1NjY0ODk3",
  "owner": "bup",
  "name": "bup",
  "full_name": "bup/bup",
  "description": "Very efficient backup system based on the git packfile format, providing fast incremental saves and global deduplication (among and within files, including virtual machine images). Please post problems or patches to the mailing list for discussion (see the end of the README below).",
  "description_ja": "gitパックファイル形式に基づく非常に効率的なバックアップシステム。高速な増分保存とグローバル重複排除（仮想マシンイメージを含むファイル間・ファイル内）を提供。問題やパッチはメーリングリストへ投稿してください（README末尾参照）。",
  "url": "https://github.com/bup/bup",
  "homepage_url": "https://bup.github.io/",
  "language": "Python",
  "license": "NOASSERTION",
  "topics": [],
  "star_count": 7314,
  "fork_count": 424,
  "is_archived": false,
  "is_fork": false,
  "created_at": "2012-09-03T22:51:40Z",
  "updated_at": "2026-04-23T17:40:10Z",
  "pushed_at": "2026-04-17T23:02:40Z",
  "deleted_at": "",
  "star_history": [
    {
      "date": "2026-04-21",
      "stars": 7314
    },
    {
      "date": "2026-04-23",
      "stars": 7314
    },
    {
      "date": "2026-04-25",
      "stars": 7314
    },
    {
      "date": "2026-04-26",
      "stars": 7314
    }
  ]
}
