{
  "repo_id": "R_kgDOJC-x-g",
  "owner": "careamics",
  "name": "careamics",
  "full_name": "careamics/careamics",
  "description": "A deep-learning library for denoising images using Noise2Void and friends, with a focus on user-experience and documentation.)",
  "url": "https://github.com/CAREamics/careamics",
  "homepage_url": "https://careamics.github.io/",
  "language": "Python",
  "license": "BSD-3-Clause",
  "topics": [
    "deep-learning",
    "denoising",
    "n2v",
    "python",
    "restoration"
  ],
  "star_count": 133,
  "fork_count": 21,
  "is_archived": false,
  "is_fork": false,
  "created_at": "2023-02-27T10:22:28Z",
  "updated_at": "2026-04-22T09:22:44Z",
  "pushed_at": "2026-04-23T16:03:19Z",
  "deleted_at": "",
  "star_history": [
    {
      "date": "2026-04-23",
      "stars": 133
    }
  ]
}
