{
  "repo_id": "R_kgDORRLIOQ",
  "owner": "caverav",
  "name": "flutterdec",
  "full_name": "caverav/flutterdec",
  "description": "The Flutter Decompiler: CLI tool that decompiles Flutter Android AOT (libapp.so) into Dart-like pseudocode, supporting obfuscated builds.",
  "description_ja": "Flutter Decompiler：Flutter Android AOT（libapp.so）をDart風の疑似コードに逆コンパイルするCLIツール。難読化ビルドにも対応。",
  "url": "https://github.com/caverav/flutterdec",
  "homepage_url": "",
  "language": "Rust",
  "license": "MIT",
  "topics": [
    "android",
    "android-security",
    "cli",
    "decompiler",
    "flutter",
    "mobile",
    "mobile-pentest",
    "mobile-pentesting",
    "mobile-security",
    "reverse-engineering"
  ],
  "star_count": 39,
  "fork_count": 3,
  "is_archived": false,
  "is_fork": false,
  "created_at": "2026-02-16T02:17:23Z",
  "updated_at": "2026-05-08T23:08:29Z",
  "pushed_at": "2026-05-04T06:41:48Z",
  "deleted_at": "",
  "star_history": [
    {
      "date": "2026-04-23",
      "stars": 34
    },
    {
      "date": "2026-04-25",
      "stars": 34
    },
    {
      "date": "2026-04-26",
      "stars": 35
    },
    {
      "date": "2026-04-28",
      "stars": 36
    },
    {
      "date": "2026-05-01",
      "stars": 36
    },
    {
      "date": "2026-05-02",
      "stars": 37
    },
    {
      "date": "2026-05-03",
      "stars": 37
    },
    {
      "date": "2026-05-04",
      "stars": 38
    },
    {
      "date": "2026-05-09",
      "stars": 39
    },
    {
      "date": "2026-05-10",
      "stars": 39
    }
  ]
}
