{
  "repo_id": "R_kgDOOouH8g",
  "owner": "cisco-open",
  "name": "forge",
  "full_name": "cisco-open/forge",
  "description": "ForgeMT is a secure, scalable GitHub Actions runner platform for ephemeral workloads. Designed for multi-tenant environments, it automates isolated runner provisioning on Kubernetes or EC2, with built-in OIDC, IAM, cost optimization, and deep observability.",
  "description_ja": "ForgeMTは、エフェメラルワークロード向けのセキュアでスケーラブルなGitHub Actionsランナープラットフォームです。マルチテナント環境向けに設計され、KubernetesまたはEC2上での隔離されたランナープロビジョニングを自動化し、OIDC・IAM・コスト最適化・高度な可観測性を備えています。",
  "url": "https://github.com/cisco-open/forge",
  "homepage_url": "https://cisco-open.github.io/forge/",
  "language": "HCL",
  "license": "Apache-2.0",
  "topics": [
    "actions-runner-controller",
    "automation",
    "aws",
    "aws-eks",
    "ci",
    "ci-cd",
    "devops",
    "devsecops",
    "ec2",
    "ephemeral",
    "github-actions",
    "infrastructure-as-code",
    "kubernetes",
    "multi-tenancy",
    "opensource",
    "runners",
    "self-hosted-runners",
    "terraform"
  ],
  "star_count": 202,
  "fork_count": 8,
  "is_archived": false,
  "is_fork": false,
  "created_at": "2025-05-12T14:54:17Z",
  "updated_at": "2026-04-19T03:44:08Z",
  "pushed_at": "2026-04-13T23:56:03Z",
  "deleted_at": "",
  "star_history": [
    {
      "date": "2026-04-23",
      "stars": 202
    },
    {
      "date": "2026-04-25",
      "stars": 202
    },
    {
      "date": "2026-04-26",
      "stars": 202
    }
  ]
}
