{
  "owner": "claimed-framework",
  "name": "claimed",
  "description": "The goal of CLAIMED is to enable low-code/no-code rapid prototyping style programming to seamlessly CI/CD into production. ",
  "url": "https://github.com/claimed-framework/claimed",
  "homepage_url": "",
  "language": "Jupyter Notebook",
  "license": "Apache-2.0",
  "topics": [
    "data-science",
    "machine-learning"
  ],
  "fork_count": 3947,
  "star_count": 2312,
  "is_archived": false,
  "star_history": [
    {
      "date": "2026-04-17",
      "stars": 2312
    }
  ]
}