{
  "repo_id": "R_kgDOOl0a1A",
  "owner": "conor-is-my-name",
  "name": "google-maps-scraper",
  "full_name": "conor-is-my-name/google-maps-scraper",
  "description": "",
  "description_ja": "",
  "url": "https://github.com/conor-is-my-name/google-maps-scraper",
  "homepage_url": "",
  "language": "Python",
  "license": "MIT",
  "topics": [],
  "star_count": 296,
  "fork_count": 66,
  "is_archived": false,
  "is_fork": false,
  "created_at": "2025-05-07T05:54:57Z",
  "updated_at": "2026-05-18T02:10:11Z",
  "pushed_at": "2026-04-14T08:16:25Z",
  "deleted_at": "",
  "star_history": [
    {
      "date": "2026-05-15",
      "stars": 295
    },
    {
      "date": "2026-05-16",
      "stars": 295
    },
    {
      "date": "2026-05-17",
      "stars": 295
    },
    {
      "date": "2026-05-18",
      "stars": 296
    }
  ]
}
