{
  "owner": "ConvoyPanel",
  "name": "panel",
  "description": "A modern platform tailored for hosting providers and enthusiasts to effortlessly interact with their servers. Seamlessly wrapping around Proxmox, Convoy is easily deployable, affordable at just $6 per node per month for commercial use, and completely free for personal and non-profit endeavors.",
  "url": "https://github.com/ConvoyPanel/panel",
  "homepage_url": "https://convoypanel.com",
  "language": "PHP",
  "license": "NOASSERTION",
  "topics": [
    "business",
    "hosting",
    "laravel",
    "panel",
    "php",
    "php8",
    "proxmox",
    "react",
    "virtualization",
    "productivity"
  ],
  "fork_count": 86,
  "star_count": 491,
  "is_archived": false,
  "star_history": [
    {
      "date": "2026-04-17",
      "stars": 491
    }
  ]
}