{
  "owner": "CYB3RMX",
  "name": "Qu1cksc0pe",
  "description": "All-in-One malware analysis tool.",
  "url": "https://github.com/CYB3RMX/Qu1cksc0pe",
  "homepage_url": "",
  "language": "YARA",
  "license": "GPL-3.0",
  "topics": [
    "linux",
    "malware-analysis",
    "python3",
    "static-analysis",
    "virustotal",
    "security-tools",
    "termux",
    "elf",
    "exe",
    "windows",
    "packer",
    "suspicious-files",
    "malware",
    "threat-analysis",
    "apk",
    "osx",
    "strings",
    "antivirus",
    "ransomware",
    "all-in-one"
  ],
  "fork_count": 254,
  "star_count": 1975,
  "is_archived": false,
  "star_history": [
    {
      "date": "2026-04-17",
      "stars": 1975
    }
  ]
}