{
  "owner": "DerekYRC",
  "name": "mini-spring-cloud",
  "description": "mini-spring-cloud is a simplified version of the Spring Cloud framework that helps you quickly familiarize yourself with Spring Cloud source code and master its core principles. While preserving Spring Cloud's core functionality, the code is streamlined as much as possible. ",
  "url": "https://github.com/DerekYRC/mini-spring-cloud",
  "homepage_url": "",
  "language": "Java",
  "license": "",
  "topics": [
    "spring",
    "springboot",
    "springcloud",
    "spring-boot",
    "spring-cloud",
    "mini-spring",
    "minispring",
    "minispringcloud",
    "mini-spring-cloud",
    "tiny-spring",
    "tinyspring",
    "eureka",
    "ribbon",
    "feign",
    "nacos"
  ],
  "fork_count": 380,
  "star_count": 1902,
  "is_archived": false,
  "star_history": [
    {
      "date": "2026-04-14",
      "stars": 1902
    }
  ]
}