{
  "repo_id": "MDEwOlJlcG9zaXRvcnk2NzYyMzgyMg==",
  "owner": "dhall-lang",
  "name": "dhall-haskell",
  "full_name": "dhall-lang/dhall-haskell",
  "description": "Maintainable configuration files",
  "description_ja": "",
  "url": "https://github.com/dhall-lang/dhall-haskell",
  "homepage_url": "https://dhall-lang.org/",
  "language": "Dhall",
  "license": "BSD-3-Clause",
  "topics": [
    "configuration-language",
    "dhall",
    "haskell"
  ],
  "star_count": 960,
  "fork_count": 220,
  "is_archived": false,
  "is_fork": false,
  "created_at": "2016-09-07T16:18:15Z",
  "updated_at": "2026-04-27T16:17:06Z",
  "pushed_at": "2026-04-27T16:17:00Z",
  "deleted_at": "",
  "star_history": [
    {
      "date": "2026-04-28",
      "stars": 960
    }
  ]
}
