{
  "repo_id": "MDEwOlJlcG9zaXRvcnkyOTg4NzQ5OQ==",
  "owner": "dkhamsing",
  "name": "open-source-ios-apps",
  "full_name": "dkhamsing/open-source-ios-apps",
  "description": ":iphone: Collaborative List of Open-Source iOS Apps",
  "description_ja": ":iphone: オープンソースiOSアプリのコラボレーティブなリスト。",
  "url": "https://github.com/dkhamsing/open-source-ios-apps",
  "homepage_url": "",
  "language": "",
  "license": "CC0-1.0",
  "topics": [
    "app",
    "apple",
    "apple-tv",
    "apple-vision-pro",
    "apple-watch",
    "awesome",
    "cocoapods",
    "example",
    "flutter",
    "game",
    "ios",
    "ipad",
    "iphone",
    "list",
    "objective-c",
    "react-native",
    "swift",
    "swiftui",
    "tvos",
    "watchos"
  ],
  "star_count": 50007,
  "fork_count": 5764,
  "is_archived": false,
  "is_fork": false,
  "created_at": "2015-01-26T23:32:34Z",
  "updated_at": "2026-04-28T19:09:54Z",
  "pushed_at": "2026-04-28T12:21:15Z",
  "deleted_at": "",
  "star_history": [
    {
      "date": "2026-04-18",
      "stars": 49800
    },
    {
      "date": "2026-04-19",
      "stars": 49816
    },
    {
      "date": "2026-04-21",
      "stars": 49877
    },
    {
      "date": "2026-04-23",
      "stars": 49924
    },
    {
      "date": "2026-04-25",
      "stars": 49957
    },
    {
      "date": "2026-04-26",
      "stars": 49975
    },
    {
      "date": "2026-04-28",
      "stars": 50007
    }
  ]
}
