{
  "owner": "executablebooks",
  "name": "MyST-Parser",
  "description": "An extended commonmark compliant parser, with bridges to docutils/sphinx",
  "url": "https://github.com/executablebooks/MyST-Parser",
  "homepage_url": "https://myst-parser.readthedocs.io",
  "language": "Python",
  "license": "MIT",
  "topics": [
    "markdown-parser",
    "docutils",
    "sphinx",
    "sphinx-extension"
  ],
  "fork_count": 228,
  "star_count": 878,
  "is_archived": false,
  "star_history": [
    {
      "date": "2026-04-14",
      "stars": 878
    }
  ]
}