{
  "repo_id": "MDEwOlJlcG9zaXRvcnk1NjQ3MTk=",
  "owner": "floere",
  "name": "phony",
  "full_name": "floere/phony",
  "description": "E164 international phone number normalizing, splitting, formatting. ",
  "url": "https://github.com/floere/phony",
  "homepage_url": "http://florianhanke.com/phony/",
  "language": "Ruby",
  "license": "MIT",
  "topics": [],
  "star_count": 1090,
  "fork_count": 240,
  "is_archived": false,
  "is_fork": false,
  "created_at": "2010-03-16T09:04:51Z",
  "updated_at": "2026-04-10T21:29:17Z",
  "pushed_at": "2026-03-26T20:14:18Z",
  "deleted_at": "",
  "star_history": [
    {
      "date": "2026-04-21",
      "stars": 1090
    }
  ]
}
