{
  "owner": "FoundationVision",
  "name": "ByteTrack",
  "description": "[ECCV 2022] ByteTrack: Multi-Object Tracking by Associating Every Detection Box",
  "url": "https://github.com/FoundationVision/ByteTrack",
  "homepage_url": "",
  "language": "Python",
  "license": "MIT",
  "topics": [
    "multi-object-tracking",
    "real-time",
    "deployment",
    "pytorch"
  ],
  "fork_count": 1109,
  "star_count": 6287,
  "is_archived": false,
  "star_history": [
    {
      "date": "2026-04-17",
      "stars": 6287
    }
  ]
}