{
  "owner": "founded-labs",
  "name": "react-native-reusables",
  "description": "Bringing shadcn/ui to React Native. Beautifully crafted components with Nativewind/Uniwind, open source, and almost as easy to use.",
  "url": "https://github.com/founded-labs/react-native-reusables",
  "homepage_url": "https://reactnativereusables.com",
  "language": "TypeScript",
  "license": "MIT",
  "topics": [
    "expo",
    "react-native",
    "react-native-web",
    "shadcn-ui",
    "radix-ui",
    "react-native-reusables",
    "shadcn",
    "ui"
  ],
  "fork_count": 291,
  "star_count": 8195,
  "is_archived": false,
  "star_history": [
    {
      "date": "2026-04-17",
      "stars": 8195
    }
  ]
}