{
  "repo_id": "MDEwOlJlcG9zaXRvcnkyNzM1MzkyMQ==",
  "owner": "has-friendship",
  "name": "has_friendship",
  "full_name": "has-friendship/has_friendship",
  "description": "Add friendship to ActiveRecord models",
  "description_ja": "ActiveRecord モデルにフレンドシップ機能を追加する",
  "url": "https://github.com/has-friendship/has_friendship",
  "homepage_url": "",
  "language": "Ruby",
  "license": "MIT",
  "topics": [
    "friendship",
    "rails",
    "ruby",
    "social-network"
  ],
  "star_count": 205,
  "fork_count": 96,
  "is_archived": false,
  "is_fork": false,
  "created_at": "2014-11-30T23:22:18Z",
  "updated_at": "2026-01-04T02:20:27Z",
  "pushed_at": "2026-01-02T01:46:34Z",
  "deleted_at": "",
  "star_history": [
    {
      "date": "2026-04-21",
      "stars": 205
    },
    {
      "date": "2026-04-23",
      "stars": 205
    },
    {
      "date": "2026-04-25",
      "stars": 205
    },
    {
      "date": "2026-04-26",
      "stars": 205
    },
    {
      "date": "2026-04-28",
      "stars": 205
    },
    {
      "date": "2026-05-01",
      "stars": 205
    },
    {
      "date": "2026-05-02",
      "stars": 205
    }
  ]
}
