{
  "repo_id": "R_kgDOJRCYTQ",
  "owner": "heywillow",
  "name": "willow",
  "full_name": "heywillow/willow",
  "description": "Open source, local, and self-hosted Amazon Echo/Google Home competitive Voice Assistant alternative",
  "description_ja": "オープンソースのローカル・セルフホスト型 Amazon Echo / Google Home 代替音声アシスタント",
  "url": "https://github.com/HeyWillow/willow",
  "homepage_url": "https://heywillow.io/",
  "language": "C",
  "license": "Apache-2.0",
  "topics": [
    "alexa",
    "deep-learning",
    "echo",
    "esp-adf",
    "esp-idf",
    "esp32",
    "google-home",
    "home-assistant",
    "home-automation",
    "privacy",
    "speech-recognition",
    "speech-to-text",
    "whisper"
  ],
  "star_count": 3018,
  "fork_count": 118,
  "is_archived": false,
  "is_fork": false,
  "created_at": "2023-03-31T14:05:15Z",
  "updated_at": "2026-04-26T16:11:56Z",
  "pushed_at": "2026-02-13T23:07:50Z",
  "deleted_at": "",
  "star_history": [
    {
      "date": "2026-04-23",
      "stars": 3016
    },
    {
      "date": "2026-04-25",
      "stars": 3017
    },
    {
      "date": "2026-04-26",
      "stars": 3018
    }
  ]
}
