{
  "owner": "ImplFerris",
  "name": "LearnRust",
  "description": "Rust Learning Resources",
  "url": "https://github.com/ImplFerris/LearnRust",
  "homepage_url": "https://implrust.com",
  "language": "",
  "license": "",
  "topics": [
    "learning",
    "programming",
    "rust",
    "rust-lang",
    "rust-programming",
    "learn-rust",
    "rust-tutorial"
  ],
  "fork_count": 198,
  "star_count": 1989,
  "is_archived": false,
  "star_history": [
    {
      "date": "2026-04-14",
      "stars": 1989
    }
  ]
}