{
  "repo_id": "R_kgDOGdYN6A",
  "owner": "javahello",
  "name": "nvim",
  "full_name": "javahello/nvim",
  "description": "nvim config",
  "description_ja": "nvim の設定",
  "url": "https://github.com/JavaHello/nvim",
  "homepage_url": "",
  "language": "Lua",
  "license": "Apache-2.0",
  "topics": [
    "ide",
    "java",
    "maven",
    "neovim",
    "nvim",
    "spring-boot"
  ],
  "star_count": 111,
  "fork_count": 13,
  "is_archived": false,
  "is_fork": false,
  "created_at": "2021-11-30T14:18:51Z",
  "updated_at": "2026-05-02T02:10:03Z",
  "pushed_at": "2026-05-02T02:09:59Z",
  "deleted_at": "",
  "star_history": [
    {
      "date": "2026-04-23",
      "stars": 111
    },
    {
      "date": "2026-04-25",
      "stars": 111
    },
    {
      "date": "2026-04-26",
      "stars": 111
    },
    {
      "date": "2026-04-28",
      "stars": 111
    },
    {
      "date": "2026-05-01",
      "stars": 111
    },
    {
      "date": "2026-05-02",
      "stars": 111
    },
    {
      "date": "2026-05-03",
      "stars": 111
    },
    {
      "date": "2026-05-04",
      "stars": 111
    }
  ]
}
