{
  "repo_id": "R_kgDOImGH6g",
  "owner": "jingmatrix",
  "name": "chromext",
  "full_name": "jingmatrix/chromext",
  "description": "UserScript and DevTools supports for Chromium based and WebView based browsers",
  "description_ja": "Chromium ベースおよび WebView ベースのブラウザ向け UserScript・DevTools サポート",
  "url": "https://github.com/JingMatrix/ChromeXt",
  "homepage_url": "https://jingmatrix.github.io/ChromeXt/",
  "language": "Kotlin",
  "license": "GPL-3.0",
  "topics": [
    "android",
    "brave",
    "brave-browser",
    "bromite",
    "browser",
    "chrome",
    "chromium",
    "chromium-browser",
    "eruda",
    "google-chrome",
    "lsposed",
    "microsoft-edge",
    "samsung-internet",
    "thorium-browser",
    "userscript",
    "vivaldi",
    "webview",
    "xposed-module"
  ],
  "star_count": 1076,
  "fork_count": 81,
  "is_archived": false,
  "is_fork": false,
  "created_at": "2022-12-11T04:17:38Z",
  "updated_at": "2026-05-12T11:35:03Z",
  "pushed_at": "2026-04-24T08:05:54Z",
  "deleted_at": "",
  "star_history": [
    {
      "date": "2026-04-21",
      "stars": 1059
    },
    {
      "date": "2026-04-23",
      "stars": 1059
    },
    {
      "date": "2026-04-25",
      "stars": 1062
    },
    {
      "date": "2026-04-26",
      "stars": 1063
    },
    {
      "date": "2026-04-28",
      "stars": 1066
    },
    {
      "date": "2026-05-01",
      "stars": 1067
    },
    {
      "date": "2026-05-02",
      "stars": 1067
    },
    {
      "date": "2026-05-03",
      "stars": 1068
    },
    {
      "date": "2026-05-04",
      "stars": 1069
    },
    {
      "date": "2026-05-09",
      "stars": 1072
    },
    {
      "date": "2026-05-10",
      "stars": 1074
    },
    {
      "date": "2026-05-11",
      "stars": 1074
    },
    {
      "date": "2026-05-12",
      "stars": 1076
    }
  ]
}
