{
  "owner": "jordond",
  "name": "compass",
  "description": "🧭 Kotlin Multiplatform library location toolkit for geocoding and geolocation",
  "url": "https://github.com/jordond/compass",
  "homepage_url": "https://compass.jordond.dev",
  "language": "Kotlin",
  "license": "MIT",
  "topics": [
    "compose",
    "compose-multiplatform",
    "geocoder",
    "geolocation",
    "kotlin",
    "kotlin-multiplatform",
    "location"
  ],
  "fork_count": 22,
  "star_count": 409,
  "is_archived": false,
  "star_history": [
    {
      "date": "2026-04-14",
      "stars": 409
    }
  ]
}