{
  "owner": "jvziyaoyao",
  "name": "scale",
  "description": "🖼 An image viewer for Android and Compose Multiplatform with transition animations and support for large images. 😄 专门为Android和Compose Multiplatform开发的图片浏览库，支持过渡变换和超大图片的显示。",
  "url": "https://github.com/jvziyaoyao/scale",
  "homepage_url": "https://jvziyaoyao.github.io/scale",
  "language": "Kotlin",
  "license": "Apache-2.0",
  "topics": [
    "jetpack-compose",
    "android",
    "androidx",
    "compose",
    "compose-multiplatform",
    "kotlin"
  ],
  "fork_count": 15,
  "star_count": 253,
  "is_archived": false,
  "star_history": [
    {
      "date": "2026-04-17",
      "stars": 253
    }
  ]
}