{
  "repo_id": "MDEwOlJlcG9zaXRvcnkyMzc2MzY2MDc=",
  "owner": "khoasuperman",
  "name": "findseat",
  "full_name": "khoasuperman/findseat",
  "description": "A Completed Functional Flutter App - FindSeat (BLoC + Json API + Unit Test + Firebase Auth)",
  "description_ja": "完成した機能的な Flutter アプリ — FindSeat（BLoC + Json API + Unit Test + Firebase Auth）。",
  "url": "https://github.com/KhoaSuperman/findseat",
  "homepage_url": "",
  "language": "Dart",
  "license": "",
  "topics": [
    "clean-architecture",
    "flutter",
    "flutter-app",
    "flutter-apps",
    "flutter-demo",
    "flutter-example-app",
    "flutter-movie",
    "flutter-movie-app",
    "flutter-ui",
    "flutterbloc",
    "real-world-project"
  ],
  "star_count": 1220,
  "fork_count": 361,
  "is_archived": false,
  "is_fork": false,
  "created_at": "2020-02-01T15:41:52Z",
  "updated_at": "2026-04-23T06:54:59Z",
  "pushed_at": "2022-03-20T17:36:58Z",
  "deleted_at": "",
  "star_history": [
    {
      "date": "2026-04-21",
      "stars": 1219
    },
    {
      "date": "2026-04-23",
      "stars": 1220
    },
    {
      "date": "2026-04-25",
      "stars": 1220
    },
    {
      "date": "2026-04-26",
      "stars": 1220
    },
    {
      "date": "2026-04-28",
      "stars": 1220
    },
    {
      "date": "2026-05-01",
      "stars": 1220
    },
    {
      "date": "2026-05-02",
      "stars": 1220
    }
  ]
}
