{
  "repo_id": "MDEwOlJlcG9zaXRvcnk5OTk0Mjc2OQ==",
  "owner": "librehardwaremonitor",
  "name": "librehardwaremonitor",
  "full_name": "librehardwaremonitor/librehardwaremonitor",
  "description": "Libre Hardware Monitor is free software that can monitor the temperature sensors, fan speeds, voltages, load and clock speeds of your computer.",
  "description_ja": "Libre Hardware Monitor は、コンピューターの温度センサー、ファン回転数、電圧、負荷、クロック速度を監視できる無料ソフトウェア。",
  "url": "https://github.com/LibreHardwareMonitor/LibreHardwareMonitor",
  "homepage_url": "",
  "language": "C#",
  "license": "MPL-2.0",
  "topics": [
    "free",
    "hacktoberfest",
    "hardware",
    "hardware-monitoring",
    "libre-hardware-monitor",
    "monitor",
    "monitoring",
    "open-source",
    "opensource",
    "system",
    "system-monitor",
    "system-monitoring"
  ],
  "star_count": 8371,
  "fork_count": 930,
  "is_archived": false,
  "is_fork": false,
  "created_at": "2017-08-10T16:19:30Z",
  "updated_at": "2026-05-18T15:28:28Z",
  "pushed_at": "2026-05-15T08:31:27Z",
  "deleted_at": "",
  "star_history": [
    {
      "date": "2026-04-21",
      "stars": 8201
    },
    {
      "date": "2026-04-23",
      "stars": 8215
    },
    {
      "date": "2026-04-25",
      "stars": 8232
    },
    {
      "date": "2026-04-26",
      "stars": 8241
    },
    {
      "date": "2026-04-28",
      "stars": 8257
    },
    {
      "date": "2026-05-01",
      "stars": 8266
    },
    {
      "date": "2026-05-02",
      "stars": 8271
    },
    {
      "date": "2026-05-03",
      "stars": 8277
    },
    {
      "date": "2026-05-04",
      "stars": 8280
    },
    {
      "date": "2026-05-09",
      "stars": 8309
    },
    {
      "date": "2026-05-10",
      "stars": 8317
    },
    {
      "date": "2026-05-11",
      "stars": 8320
    },
    {
      "date": "2026-05-12",
      "stars": 8329
    },
    {
      "date": "2026-05-14",
      "stars": 8343
    },
    {
      "date": "2026-05-15",
      "stars": 8350
    },
    {
      "date": "2026-05-16",
      "stars": 8356
    },
    {
      "date": "2026-05-17",
      "stars": 8367
    },
    {
      "date": "2026-05-18",
      "stars": 8371
    }
  ]
}
