{
  "repo_id": "R_kgDOQ02u1g",
  "owner": "lightonai",
  "name": "next-plaid",
  "full_name": "lightonai/next-plaid",
  "description": "NextPlaid, ColGREP: Multi-vector search, from database to coding agents.",
  "url": "https://github.com/lightonai/next-plaid",
  "homepage_url": "https://lightonai.github.io/next-plaid/",
  "language": "Rust",
  "license": "Apache-2.0",
  "topics": [
    "agentic-rag",
    "cli",
    "grep",
    "multi-vector",
    "vector-database"
  ],
  "star_count": 388,
  "fork_count": 44,
  "is_archived": false,
  "is_fork": false,
  "created_at": "2026-01-06T17:41:05Z",
  "updated_at": "2026-04-23T17:03:33Z",
  "pushed_at": "2026-04-22T09:55:41Z",
  "deleted_at": "",
  "star_history": [
    {
      "date": "2026-04-21",
      "stars": 383
    },
    {
      "date": "2026-04-23",
      "stars": 388
    }
  ]
}
