{
  "repo_id": "MDEwOlJlcG9zaXRvcnkxMTc2MTA2NTQ=",
  "owner": "maticzav",
  "name": "nookies",
  "full_name": "maticzav/nookies",
  "description": "🍪 A set of cookie helpers for Next.js",
  "description_ja": "🍪 Next.js 向けの Cookie ヘルパーセット",
  "url": "https://github.com/maticzav/nookies",
  "homepage_url": "",
  "language": "TypeScript",
  "license": "",
  "topics": [
    "cookie",
    "hacktoberfest",
    "nextjs",
    "react",
    "zeit"
  ],
  "star_count": 2354,
  "fork_count": 76,
  "is_archived": false,
  "is_fork": false,
  "created_at": "2018-01-16T00:32:30Z",
  "updated_at": "2026-04-26T16:43:13Z",
  "pushed_at": "2026-04-23T11:34:13Z",
  "deleted_at": "",
  "star_history": [
    {
      "date": "2026-04-23",
      "stars": 2354
    },
    {
      "date": "2026-04-25",
      "stars": 2354
    },
    {
      "date": "2026-04-26",
      "stars": 2354
    },
    {
      "date": "2026-04-28",
      "stars": 2354
    }
  ]
}
