{
  "owner": "metaplex-foundation",
  "name": "metaplex-program-library",
  "description": "Smart contracts maintained by the Metaplex team",
  "url": "https://github.com/metaplex-foundation/metaplex-program-library",
  "homepage_url": "",
  "language": "Rust",
  "license": "NOASSERTION",
  "topics": [
    "blockchain",
    "digital-assets",
    "metaplex",
    "nft",
    "solana",
    "rust"
  ],
  "fork_count": 525,
  "star_count": 648,
  "is_archived": false,
  "star_history": [
    {
      "date": "2026-04-14",
      "stars": 648
    }
  ]
}