{
  "owner": "mysql",
  "name": "mysql-connector-python",
  "description": "MySQL Connector/Python is implementing the MySQL Client/Server protocol completely in Python. No MySQL libraries are needed, and no compilation is necessary to run this Python DB API v2.0 compliant driver. Documentation \u0026 Download: http://dev.mysql.com/doc/connector-python/en",
  "url": "https://github.com/mysql/mysql-connector-python",
  "homepage_url": "",
  "language": "Python",
  "license": "NOASSERTION",
  "topics": [],
  "fork_count": 301,
  "star_count": 951,
  "is_archived": false,
  "star_history": [
    {
      "date": "2026-04-14",
      "stars": 951
    }
  ]
}