{
  "owner": "nanocurrency",
  "name": "nano-node",
  "description": "Nano is digital currency. Its ticker is: XNO and its currency symbol is: Ӿ",
  "url": "https://github.com/nanocurrency/nano-node",
  "homepage_url": "https://nano.org",
  "language": "C++",
  "license": "BSD-3-Clause",
  "topics": [
    "nano",
    "cryptocurrency",
    "cryptocurrencies",
    "nanocurrency",
    "blockchain"
  ],
  "fork_count": 802,
  "star_count": 3527,
  "is_archived": false,
  "star_history": [
    {
      "date": "2026-04-14",
      "stars": 3527
    }
  ]
}