{
  "repo_id": "R_kgDOMzx1wA",
  "owner": "nraiden",
  "name": "cofounder",
  "full_name": "nraiden/cofounder",
  "description": "ai-generated apps , full stack + generative UI",
  "description_ja": "AIが生成するアプリ — フルスタック + ジェネレーティブUI",
  "url": "https://github.com/nraiden/cofounder",
  "homepage_url": "https://cofounder.openinterface.ai/",
  "language": "TypeScript",
  "license": "MIT",
  "topics": [
    "ai",
    "api",
    "design",
    "generative",
    "javascript",
    "postgresql",
    "react",
    "tailwind",
    "typescript",
    "ui",
    "vite"
  ],
  "star_count": 6640,
  "fork_count": 723,
  "is_archived": false,
  "is_fork": false,
  "created_at": "2024-09-19T00:27:55Z",
  "updated_at": "2026-05-03T15:37:29Z",
  "pushed_at": "2024-11-08T20:47:03Z",
  "deleted_at": "",
  "star_history": [
    {
      "date": "2026-04-21",
      "stars": 6638
    },
    {
      "date": "2026-04-23",
      "stars": 6638
    },
    {
      "date": "2026-04-25",
      "stars": 6641
    },
    {
      "date": "2026-04-26",
      "stars": 6641
    },
    {
      "date": "2026-04-28",
      "stars": 6644
    },
    {
      "date": "2026-05-01",
      "stars": 6641
    },
    {
      "date": "2026-05-02",
      "stars": 6641
    },
    {
      "date": "2026-05-03",
      "stars": 6640
    }
  ]
}
