{
  "repo_id": "R_kgDOSDkRCA",
  "owner": "nuyoahwjl",
  "name": "fgic",
  "full_name": "nuyoahwjl/fgic",
  "description": "A Dockerized reproduction of the AICOMP 2025 National First Prize solution for network-supervised fine-grained image classification, using ConvNeXtv2-Large teacher models and DINOv2-Large distillation on WebFG-400 and WebiNat-5000.",
  "description_ja": "",
  "url": "https://github.com/Nuyoahwjl/FGIC",
  "homepage_url": "",
  "language": "Python",
  "license": "",
  "topics": [],
  "star_count": 47,
  "fork_count": 4,
  "is_archived": false,
  "is_fork": false,
  "created_at": "2026-04-15T16:54:32Z",
  "updated_at": "2026-05-02T04:10:24Z",
  "pushed_at": "2026-04-21T16:24:44Z",
  "deleted_at": "",
  "star_history": [
    {
      "date": "2026-04-28",
      "stars": 46
    },
    {
      "date": "2026-05-01",
      "stars": 48
    },
    {
      "date": "2026-05-02",
      "stars": 47
    }
  ]
}
