{
  "owner": "nvim-lualine",
  "name": "lualine.nvim",
  "description": "A blazing fast and easy to configure neovim statusline plugin written in pure lua.",
  "url": "https://github.com/nvim-lualine/lualine.nvim",
  "homepage_url": "",
  "language": "Lua",
  "license": "MIT",
  "topics": [
    "neovim",
    "statusline",
    "neovim-statusline",
    "nvim",
    "lua",
    "neovim-plugin",
    "neovim-lua",
    "lualine"
  ],
  "fork_count": 539,
  "star_count": 6442,
  "is_archived": false,
  "star_history": [
    {
      "date": "2026-04-14",
      "stars": 6442
    }
  ]
}