{
  "repo_id": "R_kgDOHiwQ8A",
  "owner": "outdatedguy",
  "name": "internet_connection_checker_plus",
  "full_name": "outdatedguy/internet_connection_checker_plus",
  "description": "A Flutter package to check your internet connection with sub-second response times, even on mobile networks!",
  "description_ja": "モバイルネットワーク上でもサブ秒の応答時間でインターネット接続を確認できる Flutter パッケージ",
  "url": "https://github.com/OutdatedGuy/internet_connection_checker_plus",
  "homepage_url": "https://pub.dev/packages/internet_connection_checker_plus",
  "language": "Dart",
  "license": "BSD-3-Clause",
  "topics": [
    "connectivity-checker",
    "flutter",
    "flutter-package",
    "internet",
    "internet-connection-checker",
    "internet-connection-status",
    "internet-connectivity"
  ],
  "star_count": 71,
  "fork_count": 34,
  "is_archived": false,
  "is_fork": false,
  "created_at": "2022-06-22T10:44:28Z",
  "updated_at": "2026-05-08T01:34:05Z",
  "pushed_at": "2026-05-01T20:44:48Z",
  "deleted_at": "",
  "star_history": [
    {
      "date": "2026-04-25",
      "stars": 69
    },
    {
      "date": "2026-04-26",
      "stars": 69
    },
    {
      "date": "2026-04-28",
      "stars": 69
    },
    {
      "date": "2026-05-01",
      "stars": 69
    },
    {
      "date": "2026-05-02",
      "stars": 69
    },
    {
      "date": "2026-05-03",
      "stars": 69
    },
    {
      "date": "2026-05-04",
      "stars": 69
    },
    {
      "date": "2026-05-09",
      "stars": 71
    },
    {
      "date": "2026-05-10",
      "stars": 71
    }
  ]
}
