{
  "owner": "pglombardo",
  "name": "PasswordPusher",
  "description": "🔐   Securely share sensitive information with automatic expiration \u0026 deletion after a set number of views or duration.  Track who, what and when with full audit logs.",
  "url": "https://github.com/pglombardo/PasswordPusher",
  "homepage_url": "https://docs.pwpush.com",
  "language": "Ruby",
  "license": "Apache-2.0",
  "topics": [
    "security",
    "password-expiration",
    "password",
    "password-safety",
    "communicate-passwords",
    "password-pusher",
    "ruby",
    "docker-container",
    "hacktoberfest",
    "encryption",
    "information-technology",
    "netsec",
    "netsec-tools",
    "secret",
    "security-tools",
    "self-hosted",
    "file-sharing",
    "msp",
    "upload-file"
  ],
  "fork_count": 445,
  "star_count": 2973,
  "is_archived": false,
  "star_history": [
    {
      "date": "2026-04-17",
      "stars": 2973
    }
  ]
}