{
  "repo_id": "MDEwOlJlcG9zaXRvcnk3ODYxMzczNQ==",
  "owner": "prabirshrestha",
  "name": "asyncomplete.vim",
  "full_name": "prabirshrestha/asyncomplete.vim",
  "description": "async completion in pure vim script for vim8 and neovim",
  "description_ja": "vim8およびneovim向けの純粋なVim scriptによる非同期補完",
  "url": "https://github.com/prabirshrestha/asyncomplete.vim",
  "homepage_url": "",
  "language": "Vim Script",
  "license": "MIT",
  "topics": [
    "asyncomplete",
    "code-completion",
    "neovim",
    "ultisnips",
    "vim",
    "vim8"
  ],
  "star_count": 973,
  "fork_count": 61,
  "is_archived": false,
  "is_fork": false,
  "created_at": "2017-01-11T07:27:10Z",
  "updated_at": "2026-05-09T03:55:09Z",
  "pushed_at": "2026-03-20T10:06:12Z",
  "deleted_at": "",
  "star_history": [
    {
      "date": "2026-04-21",
      "stars": 972
    },
    {
      "date": "2026-04-23",
      "stars": 972
    },
    {
      "date": "2026-04-25",
      "stars": 972
    },
    {
      "date": "2026-04-26",
      "stars": 972
    },
    {
      "date": "2026-04-28",
      "stars": 972
    },
    {
      "date": "2026-05-01",
      "stars": 972
    },
    {
      "date": "2026-05-02",
      "stars": 971
    },
    {
      "date": "2026-05-03",
      "stars": 971
    },
    {
      "date": "2026-05-04",
      "stars": 972
    },
    {
      "date": "2026-05-09",
      "stars": 973
    },
    {
      "date": "2026-05-10",
      "stars": 973
    }
  ]
}
