{
  "owner": "PrismLauncher",
  "name": "PrismLauncher",
  "description": "A custom launcher for Minecraft that allows you to easily manage multiple installations of Minecraft at once (Fork of MultiMC)",
  "url": "https://github.com/PrismLauncher/PrismLauncher",
  "homepage_url": "https://prismlauncher.org",
  "language": "C++",
  "license": "GPL-3.0",
  "topics": [
    "cpp",
    "fabricmc",
    "forge",
    "linux",
    "minecraft",
    "minecraft-launcher",
    "modrinth",
    "multimc",
    "qt",
    "qt6",
    "quiltmc",
    "prismlauncher",
    "cpp20"
  ],
  "fork_count": 1255,
  "star_count": 9117,
  "is_archived": false,
  "star_history": [
    {
      "date": "2026-04-17",
      "stars": 9117
    }
  ]
}