{
  "repo_id": "MDEwOlJlcG9zaXRvcnkxODQ3NDU2NzU=",
  "owner": "pygfx",
  "name": "pygfx",
  "full_name": "pygfx/pygfx",
  "description": "Powerful and versatile visualization for Python.",
  "description_ja": "Pythonのための強力で多用途なビジュアライゼーションツール。",
  "url": "https://github.com/pygfx/pygfx",
  "homepage_url": "https://pygfx.org",
  "language": "Python",
  "license": "BSD-2-Clause",
  "topics": [
    "3d",
    "3d-engine",
    "3d-graphics",
    "dx12",
    "graphics",
    "metal",
    "python",
    "science",
    "vizualisation",
    "vulkan",
    "wgpu"
  ],
  "star_count": 830,
  "fork_count": 71,
  "is_archived": false,
  "is_fork": false,
  "created_at": "2019-05-03T11:40:58Z",
  "updated_at": "2026-05-02T22:12:06Z",
  "pushed_at": "2026-04-22T07:40:46Z",
  "deleted_at": "",
  "star_history": [
    {
      "date": "2026-04-21",
      "stars": 827
    },
    {
      "date": "2026-04-23",
      "stars": 828
    },
    {
      "date": "2026-04-25",
      "stars": 828
    },
    {
      "date": "2026-04-26",
      "stars": 828
    },
    {
      "date": "2026-04-28",
      "stars": 828
    },
    {
      "date": "2026-05-01",
      "stars": 828
    },
    {
      "date": "2026-05-02",
      "stars": 829
    },
    {
      "date": "2026-05-03",
      "stars": 830
    },
    {
      "date": "2026-05-04",
      "stars": 830
    },
    {
      "date": "2026-05-09",
      "stars": 830
    }
  ]
}
