{
  "repo_id": "MDEwOlJlcG9zaXRvcnk4ODA2NDM1Nw==",
  "owner": "ql-win",
  "name": "quicklook",
  "full_name": "ql-win/quicklook",
  "description": "Bring macOS “Quick Look” feature to Windows",
  "description_ja": "macOSの「Quick Look」機能をWindowsに移植する",
  "url": "https://github.com/QL-Win/QuickLook",
  "homepage_url": "https://quicklookapp.vercel.app/",
  "language": "C#",
  "license": "GPL-3.0",
  "topics": [
    "quicklook"
  ],
  "star_count": 23317,
  "fork_count": 1244,
  "is_archived": false,
  "is_fork": false,
  "created_at": "2017-04-12T14:57:38Z",
  "updated_at": "2026-05-10T17:45:40Z",
  "pushed_at": "2026-05-10T18:04:16Z",
  "deleted_at": "",
  "star_history": [
    {
      "date": "2026-04-21",
      "stars": 23102
    },
    {
      "date": "2026-04-23",
      "stars": 23122
    },
    {
      "date": "2026-04-25",
      "stars": 23132
    },
    {
      "date": "2026-04-26",
      "stars": 23139
    },
    {
      "date": "2026-04-28",
      "stars": 23154
    },
    {
      "date": "2026-05-01",
      "stars": 23174
    },
    {
      "date": "2026-05-02",
      "stars": 23185
    },
    {
      "date": "2026-05-03",
      "stars": 23188
    },
    {
      "date": "2026-05-04",
      "stars": 23193
    },
    {
      "date": "2026-05-09",
      "stars": 23301
    },
    {
      "date": "2026-05-10",
      "stars": 23317
    }
  ]
}
