{
  "repo_id": "MDEwOlJlcG9zaXRvcnkzOTkzMjcwNDM=",
  "owner": "rebeccaeexu",
  "name": "awesome-high-dynamic-range-imaging",
  "full_name": "rebeccaeexu/awesome-high-dynamic-range-imaging",
  "description": "A collection of HDR imaging papers.",
  "description_ja": "HDR イメージング論文のコレクション",
  "url": "https://github.com/rebeccaeexu/Awesome-High-Dynamic-Range-Imaging",
  "homepage_url": "",
  "language": "",
  "license": "MIT",
  "topics": [
    "deep-learning",
    "hdr",
    "high-dynamic-range",
    "high-dynamic-range-imaging",
    "pytorch"
  ],
  "star_count": 233,
  "fork_count": 11,
  "is_archived": false,
  "is_fork": false,
  "created_at": "2021-08-24T03:49:21Z",
  "updated_at": "2026-05-06T11:58:16Z",
  "pushed_at": "2026-02-06T09:32:10Z",
  "deleted_at": "",
  "star_history": [
    {
      "date": "2026-04-23",
      "stars": 231
    },
    {
      "date": "2026-04-25",
      "stars": 231
    },
    {
      "date": "2026-04-26",
      "stars": 231
    },
    {
      "date": "2026-04-28",
      "stars": 231
    },
    {
      "date": "2026-05-01",
      "stars": 232
    },
    {
      "date": "2026-05-02",
      "stars": 232
    },
    {
      "date": "2026-05-03",
      "stars": 232
    },
    {
      "date": "2026-05-04",
      "stars": 232
    },
    {
      "date": "2026-05-09",
      "stars": 233
    }
  ]
}
