{
  "repo_id": "MDEwOlJlcG9zaXRvcnkyNzIxNDM2NDY=",
  "owner": "salvadordeveloper",
  "name": "flutter-tiktok",
  "full_name": "salvadordeveloper/flutter-tiktok",
  "description": "A TikTok Clone in Flutter and Firebase.",
  "description_ja": "Flutter と Firebase で作られた TikTok クローン。",
  "url": "https://github.com/salvadordeveloper/flutter-tiktok",
  "homepage_url": "",
  "language": "Dart",
  "license": "MIT",
  "topics": [],
  "star_count": 1170,
  "fork_count": 420,
  "is_archived": false,
  "is_fork": false,
  "created_at": "2020-06-14T06:08:12Z",
  "updated_at": "2026-04-25T00:45:07Z",
  "pushed_at": "2022-09-25T08:54:23Z",
  "deleted_at": "",
  "star_history": [
    {
      "date": "2026-04-21",
      "stars": 1168
    },
    {
      "date": "2026-04-23",
      "stars": 1169
    },
    {
      "date": "2026-04-25",
      "stars": 1170
    },
    {
      "date": "2026-04-26",
      "stars": 1170
    }
  ]
}
