{
  "repo_id": "MDEwOlJlcG9zaXRvcnkzNzk5NDM0OTY=",
  "owner": "shutter-network",
  "name": "rolling-shutter",
  "full_name": "shutter-network/rolling-shutter",
  "description": "A threshold encryption framework for L1 \u0026 L2 EVM-compatible chains.",
  "description_ja": "L1およびL2 EVM互換チェーン向けの閾値暗号化フレームワーク",
  "url": "https://github.com/shutter-network/rolling-shutter",
  "homepage_url": "https://twitter.com/ShutterNetwork/",
  "language": "Go",
  "license": "MIT",
  "topics": [
    "blockchain",
    "ethereum",
    "frontrunning",
    "mev",
    "rollups",
    "threshold-encryption"
  ],
  "star_count": 39,
  "fork_count": 18,
  "is_archived": false,
  "is_fork": false,
  "created_at": "2021-06-24T13:59:22Z",
  "updated_at": "2026-05-17T17:11:29Z",
  "pushed_at": "2026-05-05T13:22:45Z",
  "deleted_at": "",
  "star_history": [
    {
      "date": "2026-04-23",
      "stars": 40
    },
    {
      "date": "2026-04-25",
      "stars": 40
    },
    {
      "date": "2026-04-26",
      "stars": 40
    },
    {
      "date": "2026-04-28",
      "stars": 40
    },
    {
      "date": "2026-05-01",
      "stars": 40
    },
    {
      "date": "2026-05-02",
      "stars": 40
    },
    {
      "date": "2026-05-03",
      "stars": 40
    },
    {
      "date": "2026-05-04",
      "stars": 40
    },
    {
      "date": "2026-05-09",
      "stars": 40
    },
    {
      "date": "2026-05-10",
      "stars": 40
    },
    {
      "date": "2026-05-11",
      "stars": 40
    },
    {
      "date": "2026-05-12",
      "stars": 40
    },
    {
      "date": "2026-05-14",
      "stars": 40
    },
    {
      "date": "2026-05-15",
      "stars": 40
    },
    {
      "date": "2026-05-16",
      "stars": 40
    },
    {
      "date": "2026-05-17",
      "stars": 39
    }
  ]
}
