{
  "owner": "sindresorhus",
  "name": "Gifski",
  "description": "🌈 Convert videos to high-quality GIFs on your Mac",
  "url": "https://github.com/sindresorhus/Gifski",
  "homepage_url": "https://sindresorhus.com/gifski",
  "language": "Swift",
  "license": "MIT",
  "topics": [
    "gifski",
    "gif",
    "gif-animation",
    "video",
    "converter",
    "convert-videos",
    "macos-app",
    "macos",
    "swift",
    "swiftui",
    "app"
  ],
  "fork_count": 314,
  "star_count": 8359,
  "is_archived": false,
  "star_history": [
    {
      "date": "2026-04-14",
      "stars": 8359
    }
  ]
}