{
  "repo_id": "MDEwOlJlcG9zaXRvcnkxNTAzMDA4Nzk=",
  "owner": "snownee",
  "name": "kiwi",
  "full_name": "snownee/kiwi",
  "description": "Kiwi is a Minecraft modding library designed to help developers focus on content creation instead of repetitive work.",
  "description_ja": "KiwiはMinecraftのモッディングライブラリで、開発者が繰り返し作業ではなくコンテンツ作成に集中できるよう設計されている",
  "url": "https://github.com/Snownee/Kiwi",
  "homepage_url": "https://www.curseforge.com/minecraft/mc-mods/kiwi",
  "language": "Java",
  "license": "MIT",
  "topics": [
    "minecraft-mod"
  ],
  "star_count": 49,
  "fork_count": 11,
  "is_archived": false,
  "is_fork": false,
  "created_at": "2018-09-25T17:04:26Z",
  "updated_at": "2026-04-22T03:04:47Z",
  "pushed_at": "2026-05-04T11:43:36Z",
  "deleted_at": "",
  "star_history": [
    {
      "date": "2026-04-23",
      "stars": 49
    },
    {
      "date": "2026-04-25",
      "stars": 49
    },
    {
      "date": "2026-04-26",
      "stars": 49
    },
    {
      "date": "2026-04-28",
      "stars": 49
    },
    {
      "date": "2026-05-01",
      "stars": 49
    },
    {
      "date": "2026-05-02",
      "stars": 49
    },
    {
      "date": "2026-05-03",
      "stars": 49
    },
    {
      "date": "2026-05-04",
      "stars": 49
    },
    {
      "date": "2026-05-09",
      "stars": 49
    }
  ]
}
