{
  "repo_id": "MDEwOlJlcG9zaXRvcnkxMjc0OTIzNjY=",
  "owner": "swiftrex",
  "name": "swiftrex",
  "full_name": "swiftrex/swiftrex",
  "description": "Swift + Redux + (Combine|RxSwift|ReactiveSwift) -\u003e SwiftRex",
  "description_ja": "",
  "url": "https://github.com/SwiftRex/SwiftRex",
  "homepage_url": "https://swiftrex.github.io/SwiftRex/",
  "language": "Swift",
  "license": "Apache-2.0",
  "topics": [
    "apple",
    "combine",
    "combine-framework",
    "event-sourcing",
    "frp",
    "functional-programming",
    "observable",
    "publisher",
    "reactive-programming",
    "reactivecocoa",
    "reactiveswift",
    "reducer",
    "redux",
    "rxswift",
    "state-machine",
    "subscriber",
    "swift",
    "swiftui",
    "unidirectional-dataflow"
  ],
  "star_count": 619,
  "fork_count": 29,
  "is_archived": false,
  "is_fork": false,
  "created_at": "2018-03-31T02:37:04Z",
  "updated_at": "2026-05-16T20:59:21Z",
  "pushed_at": "2026-05-16T20:59:17Z",
  "deleted_at": "",
  "star_history": [
    {
      "date": "2026-05-15",
      "stars": 619
    },
    {
      "date": "2026-05-16",
      "stars": 619
    },
    {
      "date": "2026-05-17",
      "stars": 619
    }
  ]
}
