{
  "owner": "thesupersonic16",
  "name": "HedgeModManager",
  "description": "A mod manager for Sonic Generations, Sonic Lost World, Sonic Forces, Sonic Colours Ultimate and other PC Hedgehog Engine games.",
  "url": "https://github.com/thesupersonic16/HedgeModManager",
  "homepage_url": "",
  "language": "C#",
  "license": "MIT",
  "topics": [
    "sonic-generations",
    "sonic-lost-world",
    "sonic-forces",
    "sonic-colors-ultimate",
    "mod-manager",
    "csharp",
    "sonic-origins"
  ],
  "fork_count": 70,
  "star_count": 460,
  "is_archived": false,
  "star_history": [
    {
      "date": "2026-04-17",
      "stars": 460
    }
  ]
}