{
  "owner": "ultralytics",
  "name": "yolo-ios-app",
  "description": "Ultralytics YOLO iOS App source code for running YOLO in your own iOS apps 🌟",
  "url": "https://github.com/ultralytics/yolo-ios-app",
  "homepage_url": "https://ultralytics.com/yolo",
  "language": "Swift",
  "license": "AGPL-3.0",
  "topics": [
    "ai",
    "app",
    "app-store",
    "coreml",
    "instance-segmentation",
    "ios",
    "ml",
    "object-detection",
    "real-time",
    "swift",
    "ultralytics",
    "xcode",
    "yolo",
    "yolov8",
    "yolo11"
  ],
  "fork_count": 87,
  "star_count": 463,
  "is_archived": false,
  "star_history": [
    {
      "date": "2026-04-17",
      "stars": 463
    }
  ]
}