{
  "owner": "umputun",
  "name": "remark42",
  "description": "comment engine",
  "url": "https://github.com/umputun/remark42",
  "homepage_url": "https://remark42.com",
  "language": "Go",
  "license": "MIT",
  "topics": [
    "commenting",
    "comment-system",
    "self-hosted",
    "commenting-engines",
    "comments-widget",
    "remark42",
    "privacy"
  ],
  "fork_count": 432,
  "star_count": 5474,
  "is_archived": false,
  "star_history": [
    {
      "date": "2026-04-17",
      "stars": 5474
    }
  ]
}