{
  "owner": "voku",
  "name": "portable-utf8",
  "description": "🉑 Portable UTF-8 library - performance optimized (unicode) string functions for PHP.",
  "url": "https://github.com/voku/portable-utf8",
  "homepage_url": "",
  "language": "PHP",
  "license": "Apache-2.0",
  "topics": [
    "php",
    "string-encoding",
    "utf8",
    "utf-8",
    "unicode",
    "php7",
    "multibyte-strings",
    "multibyte",
    "ascii",
    "string",
    "string-manipulation",
    "hacktoberfest"
  ],
  "fork_count": 92,
  "star_count": 519,
  "is_archived": false,
  "star_history": [
    {
      "date": "2026-04-14",
      "stars": 519
    }
  ]
}