{
  "owner": "voquill",
  "name": "voquill",
  "description": "The open source wisprflow alternative",
  "url": "https://github.com/voquill/voquill",
  "homepage_url": "https://voquill.com/",
  "language": "TypeScript",
  "license": "NOASSERTION",
  "topics": [
    "agent",
    "agentic-ai",
    "dictation",
    "free",
    "local-ai",
    "open-source",
    "speech-to-text",
    "tauri",
    "whisper",
    "voquill",
    "superwhisper",
    "wisprflow",
    "wisprflow-alternative"
  ],
  "fork_count": 95,
  "star_count": 848,
  "is_archived": false,
  "star_history": [
    {
      "date": "2026-04-14",
      "stars": 848
    }
  ]
}