{
  "repo_id": "MDEwOlJlcG9zaXRvcnkxNTUxOTQ3NTc=",
  "owner": "waiviogit",
  "name": "waivio",
  "full_name": "waiviogit/waivio",
  "description": "",
  "description_ja": "",
  "url": "https://github.com/Waiviogit/waivio",
  "homepage_url": "",
  "language": "JavaScript",
  "license": "MIT",
  "topics": [],
  "star_count": 9,
  "fork_count": 7,
  "is_archived": false,
  "is_fork": false,
  "created_at": "2018-10-29T10:42:26Z",
  "updated_at": "2026-04-14T11:34:56Z",
  "pushed_at": "2026-04-14T12:08:28Z",
  "deleted_at": "",
  "star_history": [
    {
      "date": "2026-04-23",
      "stars": 9
    },
    {
      "date": "2026-04-25",
      "stars": 9
    },
    {
      "date": "2026-04-26",
      "stars": 9
    },
    {
      "date": "2026-04-28",
      "stars": 9
    },
    {
      "date": "2026-05-01",
      "stars": 9
    },
    {
      "date": "2026-05-02",
      "stars": 9
    },
    {
      "date": "2026-05-03",
      "stars": 9
    },
    {
      "date": "2026-05-04",
      "stars": 9
    },
    {
      "date": "2026-05-09",
      "stars": 9
    },
    {
      "date": "2026-05-10",
      "stars": 9
    },
    {
      "date": "2026-05-11",
      "stars": 9
    },
    {
      "date": "2026-05-12",
      "stars": 9
    },
    {
      "date": "2026-05-14",
      "stars": 9
    }
  ]
}
