{
  "owner": "wolph",
  "name": "python-progressbar",
  "description": "Progressbar 2 - A progress bar for Python 2 and Python 3 - \"pip install progressbar2\"",
  "url": "https://github.com/wolph/python-progressbar",
  "homepage_url": "http://progressbar-2.readthedocs.org/en/latest/",
  "language": "Python",
  "license": "BSD-3-Clause",
  "topics": [
    "python",
    "progressbar",
    "progress-bar",
    "rate",
    "eta",
    "percentage",
    "console",
    "terminal",
    "time",
    "progress",
    "bar",
    "cli",
    "gui",
    "library"
  ],
  "fork_count": 101,
  "star_count": 879,
  "is_archived": false,
  "star_history": [
    {
      "date": "2026-04-14",
      "stars": 879
    }
  ]
}