{
  "repo_id": "MDEwOlJlcG9zaXRvcnk4NzMwNjI4",
  "owner": "wuye9036",
  "name": "cpptemplatetutorial",
  "full_name": "wuye9036/cpptemplatetutorial",
  "description": "中文的C++ Template的教学指南。与知名书籍C++ Templates不同，该系列教程将C++ Templates作为一门图灵完备的语言来讲授，以求帮助读者对Meta-Programming融会贯通。(正在施工中)",
  "description_ja": "中国語によるC++ Templateの教学ガイド。著名な書籍『C++ Templates』とは異なり、このチュートリアルシリーズではC++ TemplatesをTuring完全な言語として教え、読者がMeta-Programmingを深く理解できるよう目指している。（工事中）",
  "url": "https://github.com/wuye9036/CppTemplateTutorial",
  "homepage_url": "",
  "language": "C++",
  "license": "",
  "topics": [],
  "star_count": 10544,
  "fork_count": 1622,
  "is_archived": false,
  "is_fork": false,
  "created_at": "2013-03-12T15:09:02Z",
  "updated_at": "2026-05-15T08:17:01Z",
  "pushed_at": "2024-08-20T03:11:37Z",
  "deleted_at": "",
  "star_history": [
    {
      "date": "2026-04-21",
      "stars": 10529
    },
    {
      "date": "2026-04-23",
      "stars": 10531
    },
    {
      "date": "2026-04-25",
      "stars": 10533
    },
    {
      "date": "2026-04-26",
      "stars": 10533
    },
    {
      "date": "2026-04-28",
      "stars": 10532
    },
    {
      "date": "2026-05-01",
      "stars": 10533
    },
    {
      "date": "2026-05-02",
      "stars": 10535
    },
    {
      "date": "2026-05-03",
      "stars": 10536
    },
    {
      "date": "2026-05-04",
      "stars": 10538
    },
    {
      "date": "2026-05-09",
      "stars": 10539
    },
    {
      "date": "2026-05-10",
      "stars": 10540
    },
    {
      "date": "2026-05-11",
      "stars": 10541
    },
    {
      "date": "2026-05-12",
      "stars": 10541
    },
    {
      "date": "2026-05-14",
      "stars": 10543
    },
    {
      "date": "2026-05-15",
      "stars": 10544
    }
  ]
}
